intellibricks/__init__.py
intellibricks/py.typed
intellibricks/util.py
intellibricks/agents/__init__.py
intellibricks/agents/agents.py
intellibricks/llms/__init__.py
intellibricks/llms/constants.py
intellibricks/llms/exceptions.py
intellibricks/llms/factories.py
intellibricks/llms/general_web_search.py
intellibricks/llms/runtime_mappings.py
intellibricks/llms/synapses.py
intellibricks/llms/tools.py
intellibricks/llms/types.py
intellibricks/llms/util.py
intellibricks/llms/base/__init__.py
intellibricks/llms/base/contracts.py
intellibricks/llms/base/types.py
intellibricks/llms/integrations/cerebras/__init__.py
intellibricks/llms/integrations/cerebras/cerebras.py
intellibricks/llms/integrations/deepinfra/__init__.py
intellibricks/llms/integrations/deepinfra/deepinfra.py
intellibricks/llms/integrations/google/__init__.py
intellibricks/llms/integrations/google/google.py
intellibricks/llms/integrations/google/tools.py
intellibricks/llms/integrations/groq/__init__.py
intellibricks/llms/integrations/groq/groq.py
intellibricks/llms/integrations/ollama/__init__.py
intellibricks/llms/integrations/ollama/ollama.py
intellibricks/llms/integrations/openai/__init__.py
intellibricks/llms/integrations/openai/openai.py
intellibricks/rag/__init__.py
intellibricks/rag/contracts.py
intellibricks/rag/types.py
intellibricks/rag/integrations/__init__.py
intellibricks/rag/integrations/langchain/__init__.py
intellibricks/rag/integrations/langchain/context_sources.py
intellibricks-0.10.5.dist-info/METADATA
intellibricks-0.10.5.dist-info/WHEEL
intellibricks-0.10.5.dist-info/licenses/LICENSE
intellibricks-0.10.5.dist-info/RECORD
