Metadata-Version: 2.4
Name: intellibricks
Version: 0.10.5
Summary: IntelliBricks provides a streamlined set of tools for developing AI-powered applications. It simplifies complex tasks such as interacting with LLMs, training machine learning models, and implementing Retrieval Augmented Generation (RAG). Focus on building your application logic, not wrestling with boilerplate. IntelliBricks empowers you to build intelligent applications faster and more efficiently.
Project-URL: Source, https://github.com/arthurbrenno/intellibricks
License-File: LICENSE
Requires-Python: >=3.13.0
Requires-Dist: architecture>=0.5.23
Requires-Dist: beautifulsoup4>=4.12.3
Requires-Dist: google-genai>=1.1.0
Requires-Dist: groq>=0.13.1
Requires-Dist: httpx>=0.28.1
Requires-Dist: langfuse>=2.57.0
Requires-Dist: msgspec
Requires-Dist: ollama>=0.4.7
Requires-Dist: openai>=1.54.3
Requires-Dist: python-dotenv>=1.0.1
